eph_py/__init__.py
eph_py/compute_poverty.py
eph_py/csv_data/adulto_equivalente.csv
eph_py/ephpy.py
eph_py/get_micro_data.py
eph_py/get_poverty_lines.py
eph_py-0.2.0.dist-info/WHEEL
eph_py-0.2.0.dist-info/METADATA
eph_py-0.2.0.dist-info/RECORD
