Metadata-Version: 2.1
Name: eph-py
Version: 0.2.0
Summary: 
Author: Your Name
Author-email: you@example.com
Requires-Python: >=3.9,<4.0
Classifier: Programming Language :: Python :: 3
Classifier: Programming Language :: Python :: 3.10
Classifier: Programming Language :: Python :: 3.9
Requires-Dist: pandas (>=1.3.5,<2.0.0)
Requires-Dist: pyreadr (>=0.4.4,<0.5.0)
Requires-Dist: requests (>=2.26.0,<3.0.0)
Requires-Dist: wget (>=3.2,<4.0)
